LICENSE
MANIFEST.in
README.md
requirements.txt
setup.py
data/binary/mstar/BMP2_HB03787.000
data/binary/mstar/BMP2_HB03787.001
data/binary/mstar/BMP2_HB03787.002
data/binary/mstar/BTR70_HB03787.004
data/binary/mstar/T72_HB03787.015
data/files/english_sentence.txt
data/files/english_sentence_decompressed.txt
data/files/testwritetxt.txt
data/images/dgi/characters/0_1.png
data/images/dgi/characters/1_1.png
data/images/dgi/characters/2_1.png
data/images/dgi/characters/3_1.png
data/images/dgi/characters/4_1.png
data/images/dgi/characters/5_1.png
data/images/dgi/characters/6_1.png
data/images/dgi/characters/7_1.png
data/images/dgi/characters/8_1.png
data/images/dgi/characters/9_1.png
data/images/dgi/characters/A1.png
data/images/dgi/characters/AI1.png
data/images/dgi/characters/B1.png
data/images/dgi/characters/C1.png
data/images/dgi/characters/CNN1.png
data/images/dgi/characters/D1.png
data/images/dgi/characters/DIP1.png
data/images/dgi/characters/DL1.png.png
data/images/dgi/characters/DSP1.png
data/images/dgi/characters/E1.png
data/images/dgi/characters/F1.png
data/images/dgi/characters/G1.png
data/images/dgi/characters/H1.png
data/images/dgi/characters/H11.png
data/images/dgi/characters/I1.png
data/images/dgi/characters/J1.png
data/images/dgi/characters/K1.png
data/images/dgi/characters/L1.png
data/images/dgi/characters/M1.png
data/images/dgi/characters/ML1.png
data/images/dgi/characters/N1.png
data/images/dgi/characters/O1.png
data/images/dgi/characters/P1.png
data/images/dgi/characters/Q1.png
data/images/dgi/characters/R1.png
data/images/dgi/characters/S1.png
data/images/dgi/characters/SR1.png
data/images/dgi/characters/T1.png
data/images/dgi/characters/U1.png
data/images/dgi/characters/V1.png
data/images/dgi/characters/W1.png
data/images/dgi/characters/X1.png
data/images/dgi/characters/Y1.png
data/images/dgi/characters/Z1.png
data/images/dgi/characters/add1.png
data/images/dgi/characters/alpha1.png
data/images/dgi/characters/and1.png
pyaibox.egg-info/PKG-INFO
pyaibox.egg-info/SOURCES.txt
pyaibox.egg-info/dependency_links.txt
pyaibox.egg-info/requires.txt
pyaibox.egg-info/top_level.txt
